content_accessibility_utility_on_aws/__init__.py
content_accessibility_utility_on_aws/api.py
content_accessibility_utility_on_aws/cli.py
content_accessibility_utility_on_aws/audit/__init__.py
content_accessibility_utility_on_aws/audit/api.py
content_accessibility_utility_on_aws/audit/auditor.py
content_accessibility_utility_on_aws/audit/base_check.py
content_accessibility_utility_on_aws/audit/context_collector.py
content_accessibility_utility_on_aws/audit/enhanced_checks.py
content_accessibility_utility_on_aws/audit/report_generator.py
content_accessibility_utility_on_aws/audit/standards.py
content_accessibility_utility_on_aws/audit/analyzers/__init__.py
content_accessibility_utility_on_aws/audit/analyzers/base_analyzer.py
content_accessibility_utility_on_aws/audit/checks/__init__.py
content_accessibility_utility_on_aws/audit/checks/color_contrast_checks.py
content_accessibility_utility_on_aws/audit/checks/document_language_check.py
content_accessibility_utility_on_aws/audit/checks/form_checks.py
content_accessibility_utility_on_aws/audit/checks/heading_checks.py
content_accessibility_utility_on_aws/audit/checks/image_checks.py
content_accessibility_utility_on_aws/audit/checks/link_checks.py
content_accessibility_utility_on_aws/audit/checks/structure_checks.py
content_accessibility_utility_on_aws/audit/checks/table_checks.py
content_accessibility_utility_on_aws/audit/standards/__init__.py
content_accessibility_utility_on_aws/audit/standards/issue_types.py
content_accessibility_utility_on_aws/batch/__init__.py
content_accessibility_utility_on_aws/batch/audit.py
content_accessibility_utility_on_aws/batch/common.py
content_accessibility_utility_on_aws/batch/pdf2html.py
content_accessibility_utility_on_aws/batch/remediate.py
content_accessibility_utility_on_aws/pdf2html/__init__.py
content_accessibility_utility_on_aws/pdf2html/api.py
content_accessibility_utility_on_aws/pdf2html/utils.py
content_accessibility_utility_on_aws/pdf2html/services/__init__.py
content_accessibility_utility_on_aws-0.6.2.dist-info/licenses/LICENSE
content_accessibility_utility_on_aws-0.6.2.dist-info/METADATA
content_accessibility_utility_on_aws-0.6.2.dist-info/WHEEL
content_accessibility_utility_on_aws-0.6.2.dist-info/entry_points.txt
content_accessibility_utility_on_aws-0.6.2.dist-info/top_level.txt
content_accessibility_utility_on_aws-0.6.2.dist-info/RECORD
