Metadata-Version: 2.4
Name: content-accessibility-utility-on-aws
Version: 0.6.2
Summary: The “Content Accessibility Utility on AWS” offers a comprehensive solution for modernizing web content accessibility with state-of-the-art Generative AI models, powered by Amazon Bedrock. “Content Accessibility Utility on AWS” allows users to automatically audit and remediate WCAG 2.1 accessibility compliance issues.
Author: Addie Rudy <awsrudy@amazon.com>;
License-Expression: Apache-2.0
Project-URL: Bug Tracker, https://github.com/awslabs/content-accessibility-utility-on-aws/issues
Project-URL: Documentation, https://github.com/awslabs/content-accessibility-utility-on-aws
Project-URL: Source Code, https://github.com/awslabs/content-accessibility-utility-on-aws
Classifier: Programming Language :: Python :: 3
Classifier: Programming Language :: Python :: 3.11
Classifier: Programming Language :: Python :: 3.12
Classifier: Programming Language :: Python :: 3.13
Classifier: Operating System :: OS Independent
Classifier: Topic :: Text Processing :: Markup :: HTML
Classifier: Topic :: Utilities
Requires-Python: >=3.11
License-File: LICENSE
Requires-Dist: Pillow>=11.1.0
Requires-Dist: boto3>=1.37.11
Requires-Dist: botocore>=1.37.11
Requires-Dist: beautifulsoup4>=4.11.0
Requires-Dist: bs4>=0.0.1
Requires-Dist: pydantic>=2.10.6
Requires-Dist: defusedcsv>=2.0.0
Requires-Dist: Flask>=3.1.0
Requires-Dist: PyYaml>=6.0.0
Requires-Dist: pypdf>=5.4.0
Provides-Extra: webapp
Requires-Dist: streamlit>=1.43.2; extra == "webapp"
Dynamic: license-file
